pycoho/__init__.py
pycoho/base_client.py
pycoho-0.1.1a3.dist-info/METADATA
pycoho-0.1.1a3.dist-info/WHEEL
pycoho-0.1.1a3.dist-info/LICENSE
pycoho-0.1.1a3.dist-info/RECORD
