Metadata-Version: 2.1
Name: pycoho
Version: 0.1.1a3
Summary: A Python wrapper for the UK Companies House API
Home-page: https://github.com/regoawt/pycoho
License: MIT
Keywords: wrapper,uk,companies,house,api
Author: Armand Rego
Author-email: armand@weirdsheeplabs.com
Requires-Python: >=3.8,<4.0
Classifier: Development Status :: 3 - Alpha
Classifier: Intended Audience :: Developers
Classifier: Intended Audience :: Education
Classifier: Intended Audience :: Science/Research
Classifier: License :: OSI Approved :: MIT License
Classifier: Programming Language :: Python :: 3
Classifier: Programming Language :: Python :: 3.8
Classifier: Programming Language :: Python :: 3.9
Classifier: Programming Language :: Python :: 3.10
Classifier: Programming Language :: Python :: 3.11
Requires-Dist: requests (>=2.28.1,<3.0.0)
